{
    "normal": -1,
    "client compromise": 0,
    "malware ddos": 1,
    "scan /usr/bin/nmap": 2,
    "ddos": 3,
    "failed attack framework-2.6/msfcli iis_nsiislog_po": 4,
    "no precursor client compromise exfil/sams_launch_v": 5,
    "c2 + tcp control channel exfil - no precursor nc": 6,
    "c2 + control channel exfil - no precursor nc": 7,
    "phishing email exploit/malware/trawler": 8,
    "post-phishing c2 exploit/malware/malclient.pl": 9,
    "post-phishing c2 + tcp control channel exfil explo": 10,
    "failed attack framework-2.6/msfcli cabrightstor_di": 11,
    "post-phishing c2 heartbeat exploit/malware/malclie": 12,
    "spambot client compromise": 13,
    "spambot malicious download": 14,
    "spam bot": 15,
    "post-phishing client compromise + malicious downlo": 16,
    "post-phishing c2 + tcp control channel exfil nc": 17,
    "break-DNS_1_exploit echo": 18,
    "c2 remote command execution nc": 19,
    "c2 + tcp control channel exfil nc": 20
}